geonodectl-0.3.2.dist-info/licenses/LICENSE
geonoderest/apiconf.py
geonoderest/attributes.py
geonoderest/cmdprint.py
geonoderest/datasets.py
geonoderest/documents.py
geonoderest/exceptions.py
geonoderest/executionrequest.py
geonoderest/geoapps.py
geonoderest/geonodectl.py
geonoderest/geonodeobject.py
geonoderest/geonodetypes.py
geonoderest/keywords.py
geonoderest/linkedresources.py
geonoderest/maps.py
geonoderest/resources.py
geonoderest/rest.py
geonoderest/tkeywordlabels.py
geonoderest/tkeywords.py
geonoderest/uploads.py
geonoderest/users.py
geonoderest/tests/test_ressources.py
geonodectl-0.3.2.dist-info/METADATA
geonodectl-0.3.2.dist-info/WHEEL
geonodectl-0.3.2.dist-info/entry_points.txt
geonodectl-0.3.2.dist-info/top_level.txt
geonodectl-0.3.2.dist-info/RECORD
