Metadata-Version: 2.4
Name: geonodectl
Version: 0.3.2
Summary: a commandline interface tool for Geonode Rest API v2
Author-email: marcel wallschlaeger <marcel.wallschlaeger@zalf.de>
Project-URL: repository, https://github.com/GeoNodeUserGroup-DE/geonodectl/
Requires-Python: >=3.8
License-File: LICENSE
Requires-Dist: requests==2.32.4
Requires-Dist: types-requests==2.32.0.20241016
Requires-Dist: tabulate==0.9.0
Requires-Dist: types-tabulate==0.9.0.20240106
Requires-Dist: types-urllib3==1.26.25.14
Provides-Extra: test
Requires-Dist: pre_commit==4.3.0; extra == "test"
Requires-Dist: flake8==7.0.0; extra == "test"
Requires-Dist: black==24.4.1; extra == "test"
Requires-Dist: mypy==1.10.0; extra == "test"
Dynamic: license-file
